[
  {
    "Betegazonosító típusa": "TAJ szám",
    "Beteg azonosítója": "116086200",
    "Esemény típusa": "Járóbeteg-szakellátás megkezdése",
    "Ellátás státusza": "FELVETEL",
    "Ellátás kódja": "JARO",
    "Ellátás azonosítója": "231802281282976230",
    "Ellátó osztály": "001181334",
    "Ellátás kezdete": "2018.03.26. 09:11:08",
    "Ellátó orvos": "Hársing Judit (34171)",
    "Ambuláns ellátás típusa": "visszarendelés",
    "Beutaló osztály": "402123D",
    "Beutaló orvos": "Kuzmanovszki Daniella (66811)",
    "Ambuláns naplószám": "20001504",
    "BEZÁRÁS": "EHR DOKUMENTUMOK"
  },
  {
    "Betegazonosító típusa": "TAJ szám",
    "Beteg azonosítója": "116086200",
    "Esemény típusa": "Járóbeteg-szakellátás megkezdése",
    "Ellátás státusza": "FELVETEL",
    "Ellátás kódja": "JARO",
    "Ellátás azonosítója": "231802281270975199",
    "Ellátó osztály": "001181334",
    "Ellátás kezdete": "2018.03.26. 09:11:01",
    "Ellátó orvos": "Hársing Judit (34171)",
    "Ambuláns ellátás típusa": "visszarendelés",
    "Beutaló osztály": "402123D",
    "Beutaló orvos": "Kuzmanovszki Daniella (66811)",
    "Ambuláns naplószám": "20001503",
    "BEZÁRÁS": "EHR DOKUMENTUMOK"
  },
  {
    "Betegazonosító típusa": "TAJ szám",
    "Beteg azonosítója": "116086200",
    "Esemény típusa": "Háziorvosi ellátás befejezése",
    "Ellátás státusza": "ELBOCSATAS",
    "Ellátás kódja": "HAZIORVOS",
    "Ellátás azonosítója": "231801460951390536",
    "Ellátó intézmény": "Dr Benedek György Emilné",
    "Ellátó osztály": "háziorvosi ellátás",
    "Ellátás kezdete": "2018.02.22. 16:07:00",
    "Ellátás vége": "2018.02.22. 16:08:00",
    "Ellátó orvos": "Koltay Angéla Krisztina (63714)",
    "BEZÁRÁS": "EHR DOKUMENTUMOK"
  },
  {
    "Betegazonosító típusa": "TAJ szám",
    "Beteg azonosítója": "116086200",
    "Esemény típusa": "Háziorvosi ellátás megkezdése",
    "Ellátás státusza": "FELVETEL",
    "Ellátás kódja": "HAZIORVOS",
    "Ellátás azonosítója": "231800580758883479",
    "Ellátó intézmény": "Dr Benedek György Emilné",
    "Ellátó osztály": "háziorvosi ellátás",
    "Ellátás kezdete": "2018.01.23. 15:24:00",
    "Ellátó orvos": "Solynóczki Katalin (41492)",
    "BEZÁRÁS": "EHR DOKUMENTUMOK"
  },
  {
    "Betegazonosító típusa": "TAJ szám",
    "Beteg azonosítója": "116086200",
    "Esemény típusa": "Háziorvosi ellátás befejezése",
    "Ellátás státusza": "ELBOCSATAS",
    "Ellátás kódja": "HAZIORVOS",
    "Ellátás azonosítója": "231700829414512946",
    "Ellátó intézmény": "Dr Benedek György Emilné",
    "Ellátó osztály": "háziorvosi ellátás",
    "Ellátás kezdete": "2017.12.19. 16:28:00",
    "Ellátás vége": "2017.12.19. 16:30:00",
    "Ellátó orvos": "Solynóczki Katalin (41492)",
    "BEZÁRÁS": "EHR DOKUMENTUMOK"
  },
  {
    "Betegazonosító típusa": "TAJ szám",
    "Beteg azonosítója": "116086200",
    "Esemény típusa": "Járóbeteg-szakellátás befejezése",
    "Ellátás státusza": "ELBOCSATAS",
    "Ellátás kódja": "JARO",
    "Ellátás azonosítója": "231809193999709856",
    "Ellátó intézmény": "ÉSZAK-BUDAI SZENT JÁNOS CENTRUMKÓRHÁZ",
    "Ellátó osztály": "Ortopédiai szakambulancia",
    "Ellátás kezdete": "2018.12.03. 08:57:00",
    "Ellátás vége": "2018.12.03. 13:08:00",
    "Ellátó orvos": "Nadianmehr Behzad (73968)",
    "Ambuláns ellátás típusa": "első szakellátás az adott betegséggel kapcsolatban",
    "Beutaló intézmény": "ÉSZAK-BUDAI SZENT JÁNOS CENTRUMKÓRHÁZ",
    "Beutaló osztály": "Ortopédiai szakambulancia",
    "Beutaló orvos": "Nadianmehr Behzad (73968)",
    "Iránydiagnózis": "A boka zúzódása (S9000)",
    "Ambuláns naplószám": "01008959",
    "BEZÁRÁS": "EHR DOKUMENTUMOK"
  },
  {
    "Betegazonosító típusa": "TAJ szám",
    "Beteg azonosítója": "116086200",
    "Esemény típusa": "Járóbeteg-szakellátás befejezése",
    "Ellátás státusza": "ELBOCSATAS",
    "Ellátás kódja": "JARO",
    "Ellátás azonosítója": "231808825237773059",
    "Ellátó intézmény": "ÉSZAK-BUDAI SZENT JÁNOS CENTRUMKÓRHÁZ",
    "Ellátó osztály": "Integrált Radiológiai Osztály - Röntgendiagnosztika",
    "Ellátás kezdete": "2018.11.21. 11:16:00",
    "Ellátás vége": "2018.11.21. 11:16:00",
    "Ellátó orvos": "Ajzert Judit (43329)",
    "Ambuláns ellátás típusa": "első szakellátás az adott betegséggel kapcsolatban",
    "Beutaló intézmény": "ÉSZAK-BUDAI SZENT JÁNOS CENTRUMKÓRHÁZ",
    "Beutaló osztály": "Ortopédiai - Traumatológiai Szakambulancia",
    "Beutaló orvos": "Nadianmehr Behzad (73968)",
    "Iránydiagnózis": "A boka zúzódása (S9000)",
    "Ambuláns naplószám": "05011952",
    "BEZÁRÁS": "EHR DOKUMENTUMOK"
  },
  {
    "Betegazonosító típusa": "TAJ szám",
    "Beteg azonosítója": "116086200",
    "Esemény típusa": "Járóbeteg-szakellátás befejezése",
    "Ellátás státusza": "ELBOCSATAS",
    "Ellátás kódja": "JARO",
    "Ellátás azonosítója": "231808823003751483",
    "Ellátó intézmény": "ÉSZAK-BUDAI SZENT JÁNOS CENTRUMKÓRHÁZ",
    "Ellátó osztály": "Ortopédiai - Traumatológiai Szakambulancia",
    "Ellátás kezdete": "2018.11.21. 10:51:00",
    "Ellátás vége": "2018.11.21. 13:11:00",
    "Ellátó orvos": "Nadianmehr Behzad (73968)",
    "Ambuláns ellátás típusa": "első szakellátás az adott betegséggel kapcsolatban",
    "Beutaló intézmény": "ÉSZAK-BUDAI SZENT JÁNOS CENTRUMKÓRHÁZ",
    "Beutaló osztály": "Ortopédiai - Traumatológiai Szakambulancia",
    "Beutaló orvos": "Nadianmehr Behzad (73968)",
    "Iránydiagnózis": "A boka zúzódása (S9000)",
    "Ambuláns naplószám": "01007497",
    "BEZÁRÁS": "EHR DOKUMENTUMOK"
  },
  {
    "Betegazonosító típusa": "TAJ szám",
    "Beteg azonosítója": "116086200",
    "Esemény típusa": "Járóbeteg-szakellátás megkezdése",
    "Ellátás státusza": "FELVETEL",
    "Ellátás kódja": "JARO",
    "Ellátás azonosítója": "231802281282976230",
    "Ellátó osztály": "001181334",
    "Ellátás kezdete": "2018.03.26. 09:11:08",
    "Ellátó orvos": "Hársing Judit (34171)",
    "Ambuláns ellátás típusa": "visszarendelés",
    "Beutaló osztály": "402123D",
    "Beutaló orvos": "Kuzmanovszki Daniella (66811)",
    "Ambuláns naplószám": "20001504",
    "BEZÁRÁS": "EHR DOKUMENTUMOK"
  },
  {
    "Betegazonosító típusa": "TAJ szám",
    "Beteg azonosítója": "116086200",
    "Esemény típusa": "Járóbeteg-szakellátás megkezdése",
    "Ellátás státusza": "FELVETEL",
    "Ellátás kódja": "JARO",
    "Ellátás azonosítója": "231802281270975199",
    "Ellátó osztály": "001181334",
    "Ellátás kezdete": "2018.03.26. 09:11:01",
    "Ellátó orvos": "Hársing Judit (34171)",
    "Ambuláns ellátás típusa": "visszarendelés",
    "Beutaló osztály": "402123D",
    "Beutaló orvos": "Kuzmanovszki Daniella (66811)",
    "Ambuláns naplószám": "20001503",
    "BEZÁRÁS": "EHR DOKUMENTUMOK"
  },
  {
    "Betegazonosító típusa": "TAJ szám",
    "Beteg azonosítója": "116086200",
    "Esemény típusa": "Háziorvosi ellátás megkezdése",
    "Ellátás státusza": "FELVETEL",
    "Ellátás kódja": "HAZIORVOS",
    "Ellátás azonosítója": "231800580758883479",
    "Ellátó intézmény": "Dr Benedek György Emilné",
    "Ellátó osztály": "háziorvosi ellátás",
    "Ellátás kezdete": "2018.01.23. 15:24:00",
    "Ellátó orvos": "Solynóczki Katalin (41492)",
    "BEZÁRÁS": "EHR DOKUMENTUMOK"
  },
  {
    "Betegazonosító típusa": "TAJ szám",
    "Beteg azonosítója": "116086200",
    "Esemény típusa": "Járóbeteg-szakellátás megkezdése",
    "Ellátás státusza": "FELVETEL",
    "Ellátás kódja": "JARO",
    "Ellátás azonosítója": "231802281282976230",
    "Ellátó osztály": "001181334",
    "Ellátás kezdete": "2018.03.26. 09:11:08",
    "Ellátó orvos": "Hársing Judit (34171)",
    "Ambuláns ellátás típusa": "visszarendelés",
    "Beutaló osztály": "402123D",
    "Beutaló orvos": "Kuzmanovszki Daniella (66811)",
    "Ambuláns naplószám": "20001504",
    "BEZÁRÁS": "EHR DOKUMENTUMOK"
  },
  {
    "Betegazonosító típusa": "TAJ szám",
    "Beteg azonosítója": "116086200",
    "Esemény típusa": "Járóbeteg-szakellátás megkezdése",
    "Ellátás státusza": "FELVETEL",
    "Ellátás kódja": "JARO",
    "Ellátás azonosítója": "231802281270975199",
    "Ellátó osztály": "001181334",
    "Ellátás kezdete": "2018.03.26. 09:11:01",
    "Ellátó orvos": "Hársing Judit (34171)",
    "Ambuláns ellátás típusa": "visszarendelés",
    "Beutaló osztály": "402123D",
    "Beutaló orvos": "Kuzmanovszki Daniella (66811)",
    "Ambuláns naplószám": "20001503",
    "BEZÁRÁS": "EHR DOKUMENTUMOK"
  },
  {
    "Betegazonosító típusa": "TAJ szám",
    "Beteg azonosítója": "116086200",
    "Esemény típusa": "Háziorvosi ellátás megkezdése",
    "Ellátás státusza": "FELVETEL",
    "Ellátás kódja": "HAZIORVOS",
    "Ellátás azonosítója": "231800580758883479",
    "Ellátó intézmény": "Dr Benedek György Emilné",
    "Ellátó osztály": "háziorvosi ellátás",
    "Ellátás kezdete": "2018.01.23. 15:24:00",
    "Ellátó orvos": "Solynóczki Katalin (41492)",
    "BEZÁRÁS": "EHR DOKUMENTUMOK"
  },
  {
    "Betegazonosító típusa": "TAJ szám",
    "Beteg azonosítója": "116086200",
    "Esemény típusa": "Háziorvosi ellátás befejezése",
    "Ellátás státusza": "ELBOCSATAS",
    "Ellátás kódja": "HAZIORVOS",
    "Ellátás azonosítója": "231907479187806343",
    "Ellátó intézmény": "Dr Benedek György Emilné",
    "Ellátó osztály": "háziorvosi ellátás",
    "Ellátás kezdete": "2019.08.16. 10:40:00",
    "Ellátás vége": "2019.08.16. 10:43:00",
    "Ellátó orvos": "Kádár-Németh Krisztián Dávid (70669)",
    "BEZÁRÁS": "EHR DOKUMENTUMOK"
  },
  {
    "Betegazonosító típusa": "TAJ szám",
    "Beteg azonosítója": "116086200",
    "Esemény típusa": "Járóbeteg-szakellátás megkezdése",
    "Ellátás státusza": "FELVETEL",
    "Ellátás kódja": "JARO",
    "Ellátás azonosítója": "231802281282976230",
    "Ellátó osztály": "001181334",
    "Ellátás kezdete": "2018.03.26. 09:11:08",
    "Ellátó orvos": "Hársing Judit (34171)",
    "Ambuláns ellátás típusa": "visszarendelés",
    "Beutaló osztály": "402123D",
    "Beutaló orvos": "Kuzmanovszki Daniella (66811)",
    "Ambuláns naplószám": "20001504",
    "BEZÁRÁS": "EHR DOKUMENTUMOK"
  },
  {
    "Betegazonosító típusa": "TAJ szám",
    "Beteg azonosítója": "116086200",
    "Esemény típusa": "Járóbeteg-szakellátás megkezdése",
    "Ellátás státusza": "FELVETEL",
    "Ellátás kódja": "JARO",
    "Ellátás azonosítója": "231802281270975199",
    "Ellátó osztály": "001181334",
    "Ellátás kezdete": "2018.03.26. 09:11:01",
    "Ellátó orvos": "Hársing Judit (34171)",
    "Ambuláns ellátás típusa": "visszarendelés",
    "Beutaló osztály": "402123D",
    "Beutaló orvos": "Kuzmanovszki Daniella (66811)",
    "Ambuláns naplószám": "20001503",
    "BEZÁRÁS": "EHR DOKUMENTUMOK"
  },
  {
    "Betegazonosító típusa": "TAJ szám",
    "Beteg azonosítója": "116086200",
    "Esemény típusa": "Háziorvosi ellátás megkezdése",
    "Ellátás státusza": "FELVETEL",
    "Ellátás kódja": "HAZIORVOS",
    "Ellátás azonosítója": "231800580758883479",
    "Ellátó intézmény": "Dr Benedek György Emilné",
    "Ellátó osztály": "háziorvosi ellátás",
    "Ellátás kezdete": "2018.01.23. 15:24:00",
    "Ellátó orvos": "Solynóczki Katalin (41492)",
    "BEZÁRÁS": "EHR DOKUMENTUMOK"
  },
  {
    "Betegazonosító típusa": "TAJ szám",
    "Beteg azonosítója": "116086200",
    "Esemény típusa": "Járóbeteg-szakellátás megkezdése",
    "Ellátás státusza": "FELVETEL",
    "Ellátás kódja": "JARO",
    "Ellátás azonosítója": "231802281282976230",
    "Ellátó osztály": "001181334",
    "Ellátás kezdete": "2018.03.26. 09:11:08",
    "Ellátó orvos": "Hársing Judit (34171)",
    "Ambuláns ellátás típusa": "visszarendelés",
    "Beutaló osztály": "402123D",
    "Beutaló orvos": "Kuzmanovszki Daniella (66811)",
    "Ambuláns naplószám": "20001504",
    "BEZÁRÁS": "EHR DOKUMENTUMOK"
  },
  {
    "Betegazonosító típusa": "TAJ szám",
    "Beteg azonosítója": "116086200",
    "Esemény típusa": "Járóbeteg-szakellátás megkezdése",
    "Ellátás státusza": "FELVETEL",
    "Ellátás kódja": "JARO",
    "Ellátás azonosítója": "231802281270975199",
    "Ellátó osztály": "001181334",
    "Ellátás kezdete": "2018.03.26. 09:11:01",
    "Ellátó orvos": "Hársing Judit (34171)",
    "Ambuláns ellátás típusa": "visszarendelés",
    "Beutaló osztály": "402123D",
    "Beutaló orvos": "Kuzmanovszki Daniella (66811)",
    "Ambuláns naplószám": "20001503",
    "BEZÁRÁS": "EHR DOKUMENTUMOK"
  },
  {
    "Betegazonosító típusa": "TAJ szám",
    "Beteg azonosítója": "116086200",
    "Esemény típusa": "Háziorvosi ellátás megkezdése",
    "Ellátás státusza": "FELVETEL",
    "Ellátás kódja": "HAZIORVOS",
    "Ellátás azonosítója": "231800580758883479",
    "Ellátó intézmény": "Dr Benedek György Emilné",
    "Ellátó osztály": "háziorvosi ellátás",
    "Ellátás kezdete": "2018.01.23. 15:24:00",
    "Ellátó orvos": "Solynóczki Katalin (41492)",
    "BEZÁRÁS": "EHR DOKUMENTUMOK"
  },
  {
    "Betegazonosító típusa": "TAJ szám",
    "Beteg azonosítója": "116086200",
    "Esemény típusa": "Járóbeteg-szakellátás megkezdése",
    "Ellátás státusza": "FELVETEL",
    "Ellátás kódja": "JARO",
    "Ellátás azonosítója": "231802281282976230",
    "Ellátó osztály": "001181334",
    "Ellátás kezdete": "2018.03.26. 09:11:08",
    "Ellátó orvos": "Hársing Judit (34171)",
    "Ambuláns ellátás típusa": "visszarendelés",
    "Beutaló osztály": "402123D",
    "Beutaló orvos": "Kuzmanovszki Daniella (66811)",
    "Ambuláns naplószám": "20001504",
    "BEZÁRÁS": "EHR DOKUMENTUMOK"
  },
  {
    "Betegazonosító típusa": "TAJ szám",
    "Beteg azonosítója": "116086200",
    "Esemény típusa": "Járóbeteg-szakellátás megkezdése",
    "Ellátás státusza": "FELVETEL",
    "Ellátás kódja": "JARO",
    "Ellátás azonosítója": "231802281270975199",
    "Ellátó osztály": "001181334",
    "Ellátás kezdete": "2018.03.26. 09:11:01",
    "Ellátó orvos": "Hársing Judit (34171)",
    "Ambuláns ellátás típusa": "visszarendelés",
    "Beutaló osztály": "402123D",
    "Beutaló orvos": "Kuzmanovszki Daniella (66811)",
    "Ambuláns naplószám": "20001503",
    "BEZÁRÁS": "EHR DOKUMENTUMOK"
  },
  {
    "Betegazonosító típusa": "TAJ szám",
    "Beteg azonosítója": "116086200",
    "Esemény típusa": "Háziorvosi ellátás megkezdése",
    "Ellátás státusza": "FELVETEL",
    "Ellátás kódja": "HAZIORVOS",
    "Ellátás azonosítója": "231800580758883479",
    "Ellátó intézmény": "Dr Benedek György Emilné",
    "Ellátó osztály": "háziorvosi ellátás",
    "Ellátás kezdete": "2018.01.23. 15:24:00",
    "Ellátó orvos": "Solynóczki Katalin (41492)",
    "BEZÁRÁS": "EHR DOKUMENTUMOK"
  },
  {
    "Betegazonosító típusa": "TAJ szám",
    "Beteg azonosítója": "116086200",
    "Esemény típusa": "Járóbeteg-szakellátás befejezése",
    "Ellátás státusza": "ELBOCSATAS",
    "Ellátás kódja": "JARO",
    "Ellátás azonosítója": "232102098575673194",
    "Ellátó intézmény": "ÉSZAK-BUDAI SZENT JÁNOS CENTRUMKÓRHÁZ",
    "Ellátó osztály": "Integrált Radiológiai Osztály - Ultrahang diagnosztika",
    "Ellátás kezdete": "2021.02.22. 15:58:00",
    "Ellátás vége": "2021.02.22. 16:24:00",
    "Ellátó orvos": "Hidas Katalin (40599)",
    "Ambuláns ellátás típusa": "első szakellátás az adott betegséggel kapcsolatban",
    "Beutaló intézmény": "Dr Benedek György Emilné",
    "Beutaló osztály": "háziorvosi ellátás",
    "Beutaló orvos": "Solynóczki Katalin (41492)",
    "Iránydiagnózis": "Az alhas egyéb részeire lokalizált fájdalom (R1030)",
    "Ambuláns továbbküldés": "továbbküldés nem történt",
    "Ambuláns naplószám": "01002049",
    "Páciens megyéje": "Pest",
    "Páciens városa": "Nagykovácsi",
    "Páciens irányítószáma": "2094",
    "Páciens életkora": "21",
    "BEZÁRÁS": "EHR DOKUMENTUMOK"
  },
  {
    "Betegazonosító típusa": "TAJ szám",
    "Beteg azonosítója": "116086200",
    "Esemény típusa": "Háziorvosi ellátás befejezése",
    "Ellátás státusza": "ELBOCSATAS",
    "Ellátás kódja": "HAZIORVOS",
    "Ellátás azonosítója": "232101300927465258",
    "Ellátó intézmény": "Dr Benedek György Emilné",
    "Ellátó osztály": "háziorvosi ellátás",
    "Ellátás kezdete": "2021.02.03. 13:01:00",
    "Ellátás vége": "2021.02.03. 13:06:00",
    "Ellátó orvos": "Solynóczki Katalin (41492)",
    "Páciens megyéje": "Pest",
    "Páciens városa": "Nagykovácsi",
    "Páciens irányítószáma": "2094",
    "Páciens életkora": "22",
    "BEZÁRÁS": "EHR DOKUMENTUMOK"
  },
  {
    "Betegazonosító típusa": "TAJ szám",
    "Beteg azonosítója": "116086200",
    "Esemény típusa": "Járóbeteg-szakellátás megkezdése",
    "Ellátás státusza": "FELVETEL",
    "Ellátás kódja": "JARO",
    "Ellátás azonosítója": "231802281282976230",
    "Ellátó osztály": "001181334",
    "Ellátás kezdete": "2018.03.26. 09:11:08",
    "Ellátó orvos": "Hársing Judit (34171)",
    "Ambuláns ellátás típusa": "visszarendelés",
    "Beutaló osztály": "402123D",
    "Beutaló orvos": "Kuzmanovszki Daniella (66811)",
    "Ambuláns naplószám": "20001504",
    "BEZÁRÁS": "EHR DOKUMENTUMOK"
  },
  {
    "Betegazonosító típusa": "TAJ szám",
    "Beteg azonosítója": "116086200",
    "Esemény típusa": "Járóbeteg-szakellátás megkezdése",
    "Ellátás státusza": "FELVETEL",
    "Ellátás kódja": "JARO",
    "Ellátás azonosítója": "231802281270975199",
    "Ellátó osztály": "001181334",
    "Ellátás kezdete": "2018.03.26. 09:11:01",
    "Ellátó orvos": "Hársing Judit (34171)",
    "Ambuláns ellátás típusa": "visszarendelés",
    "Beutaló osztály": "402123D",
    "Beutaló orvos": "Kuzmanovszki Daniella (66811)",
    "Ambuláns naplószám": "20001503",
    "BEZÁRÁS": "EHR DOKUMENTUMOK"
  },
  {
    "Betegazonosító típusa": "TAJ szám",
    "Beteg azonosítója": "116086200",
    "Esemény típusa": "Háziorvosi ellátás megkezdése",
    "Ellátás státusza": "FELVETEL",
    "Ellátás kódja": "HAZIORVOS",
    "Ellátás azonosítója": "231800580758883479",
    "Ellátó intézmény": "Dr Benedek György Emilné",
    "Ellátó osztály": "háziorvosi ellátás",
    "Ellátás kezdete": "2018.01.23. 15:24:00",
    "Ellátó orvos": "Solynóczki Katalin (41492)",
    "BEZÁRÁS": "EHR DOKUMENTUMOK"
  },
  {
    "Betegazonosító típusa": "TAJ szám",
    "Beteg azonosítója": "116086200",
    "Esemény típusa": "Covidvedooltas",
    "Ellátás státusza": "ESEMENY",
    "Ellátás kódja": "OLTAS",
    "Ellátás azonosítója": "PORTAL_E029453_20210622170700_7764",
    "Ellátó intézmény": "VISEGRÁDI SZENT KOZMA ÉS DAMJÁN REHABILITÁCIÓS SZAKKÓRHÁZ ÉS GYÓGYFÜRDŐ",
    "Ellátó osztály": "II. Rehabilitációs medicina alaptevékenységek Osztálya",
    "Ellátás kezdete": "2021.06.22. 17:07:00",
    "Ellátás vége": "2021.06.22. 17:07:00",
    "Ellátó orvos": "Sárosi Kriszta (41386)",
    "EHR dokumentum típus": "COVID-19 Oltási lap",
    "BEZÁRÁS": "EHR DOKUMENTUMOK"
  },
  {
    "Betegazonosító típusa": "TAJ szám",
    "Beteg azonosítója": "116086200",
    "Esemény típusa": "Covidvedooltas",
    "Ellátás státusza": "ESEMENY",
    "Ellátás kódja": "OLTAS",
    "Ellátás azonosítója": "PORTAL_E029453_20210518164934_7739",
    "Ellátó intézmény": "VISEGRÁDI SZENT KOZMA ÉS DAMJÁN REHABILITÁCIÓS SZAKKÓRHÁZ ÉS GYÓGYFÜRDŐ",
    "Ellátó osztály": "II. Rehabilitációs medicina alaptevékenységek Osztálya",
    "Ellátás kezdete": "2021.05.18. 16:49:34",
    "Ellátás vége": "2021.05.18. 16:49:34",
    "Ellátó orvos": "Telkes Zoltán (28157)",
    "EHR dokumentum típus": "COVID-19 Oltási lap",
    "BEZÁRÁS": "EHR DOKUMENTUMOK"
  },
  {
    "Betegazonosító típusa": "TAJ szám",
    "Beteg azonosítója": "116086200",
    "Esemény típusa": "Járóbeteg-szakellátás megkezdése",
    "Ellátás státusza": "FELVETEL",
    "Ellátás kódja": "JARO",
    "Ellátás azonosítója": "231802281282976230",
    "Ellátó osztály": "001181334",
    "Ellátás kezdete": "2018.03.26. 09:11:08",
    "Ellátó orvos": "Hársing Judit (34171)",
    "Ambuláns ellátás típusa": "visszarendelés",
    "Beutaló osztály": "402123D",
    "Beutaló orvos": "Kuzmanovszki Daniella (66811)",
    "Ambuláns naplószám": "20001504",
    "BEZÁRÁS": "EHR DOKUMENTUMOK"
  },
  {
    "Betegazonosító típusa": "TAJ szám",
    "Beteg azonosítója": "116086200",
    "Esemény típusa": "Járóbeteg-szakellátás megkezdése",
    "Ellátás státusza": "FELVETEL",
    "Ellátás kódja": "JARO",
    "Ellátás azonosítója": "231802281270975199",
    "Ellátó osztály": "001181334",
    "Ellátás kezdete": "2018.03.26. 09:11:01",
    "Ellátó orvos": "Hársing Judit (34171)",
    "Ambuláns ellátás típusa": "visszarendelés",
    "Beutaló osztály": "402123D",
    "Beutaló orvos": "Kuzmanovszki Daniella (66811)",
    "Ambuláns naplószám": "20001503",
    "BEZÁRÁS": "EHR DOKUMENTUMOK"
  },
  {
    "Betegazonosító típusa": "TAJ szám",
    "Beteg azonosítója": "116086200",
    "Esemény típusa": "Háziorvosi ellátás megkezdése",
    "Ellátás státusza": "FELVETEL",
    "Ellátás kódja": "HAZIORVOS",
    "Ellátás azonosítója": "231800580758883479",
    "Ellátó intézmény": "Dr Benedek György Emilné",
    "Ellátó osztály": "háziorvosi ellátás",
    "Ellátás kezdete": "2018.01.23. 15:24:00",
    "Ellátó orvos": "Solynóczki Katalin (41492)",
    "BEZÁRÁS": "EHR DOKUMENTUMOK"
  },
  {
    "Betegazonosító típusa": "TAJ szám",
    "Beteg azonosítója": "116086200",
    "Esemény típusa": "Covidvedooltas",
    "Ellátás státusza": "ESEMENY",
    "Ellátás kódja": "OLTAS",
    "Ellátás azonosítója": "PORTAL_E220300_20211206173302_9498",
    "Ellátó intézmény": "BUDAPESTI SZENT FERENC KORHÁZ",
    "Ellátó osztály": "Kardiológiai járóbeteg szakrendelés",
    "Ellátás kezdete": "2021.12.06. 17:33:02",
    "Ellátás vége": "2021.12.06. 17:33:02",
    "Ellátó orvos": "Bacsa Melinda (76086)",
    "EHR dokumentum típus": "COVID-19 Oltási lap",
    "BEZÁRÁS": "EHR DOKUMENTUMOK"
  },
  {
    "Betegazonosító típusa": "TAJ szám",
    "Beteg azonosítója": "116086200",
    "Esemény típusa": "Járóbeteg-szakellátás megkezdése",
    "Ellátás státusza": "FELVETEL",
    "Ellátás kódja": "JARO",
    "Ellátás azonosítója": "231802281282976230",
    "Ellátó osztály": "001181334",
    "Ellátás kezdete": "2018.03.26. 09:11:08",
    "Ellátó orvos": "Hársing Judit (34171)",
    "Ambuláns ellátás típusa": "visszarendelés",
    "Beutaló osztály": "402123D",
    "Beutaló orvos": "Kuzmanovszki Daniella (66811)",
    "Ambuláns naplószám": "20001504",
    "BEZÁRÁS": "EHR DOKUMENTUMOK"
  },
  {
    "Betegazonosító típusa": "TAJ szám",
    "Beteg azonosítója": "116086200",
    "Esemény típusa": "Járóbeteg-szakellátás megkezdése",
    "Ellátás státusza": "FELVETEL",
    "Ellátás kódja": "JARO",
    "Ellátás azonosítója": "231802281270975199",
    "Ellátó osztály": "001181334",
    "Ellátás kezdete": "2018.03.26. 09:11:01",
    "Ellátó orvos": "Hársing Judit (34171)",
    "Ambuláns ellátás típusa": "visszarendelés",
    "Beutaló osztály": "402123D",
    "Beutaló orvos": "Kuzmanovszki Daniella (66811)",
    "Ambuláns naplószám": "20001503",
    "BEZÁRÁS": "EHR DOKUMENTUMOK"
  },
  {
    "Betegazonosító típusa": "TAJ szám",
    "Beteg azonosítója": "116086200",
    "Esemény típusa": "Háziorvosi ellátás megkezdése",
    "Ellátás státusza": "FELVETEL",
    "Ellátás kódja": "HAZIORVOS",
    "Ellátás azonosítója": "231800580758883479",
    "Ellátó intézmény": "Dr Benedek György Emilné",
    "Ellátó osztály": "háziorvosi ellátás",
    "Ellátás kezdete": "2018.01.23. 15:24:00",
    "Ellátó orvos": "Solynóczki Katalin (41492)",
    "BEZÁRÁS": "EHR DOKUMENTUMOK"
  },
  {
    "Betegazonosító típusa": "TAJ szám",
    "Beteg azonosítója": "116086200",
    "Esemény típusa": "Háziorvosi ellátás befejezése",
    "Ellátás státusza": "ELBOCSATAS",
    "Ellátás kódja": "HAZIORVOS",
    "Ellátás azonosítója": "232206054968851498",
    "Ellátó intézmény": "Dr Benedek György Emilné",
    "Ellátó osztály": "háziorvosi ellátás",
    "Ellátás kezdete": "2022.04.29. 10:21:00",
    "Ellátás vége": "2022.04.29. 10:34:00",
    "Ellátó orvos": "Solynóczki Katalin (41492)",
    "Ápolást indokló fődiagnózis": "Psoriasis vulgaris (L4000)",
    "Páciens megyéje": "Pest",
    "Páciens városa": "Nagykovácsi",
    "Páciens irányítószáma": "2094",
    "Páciens életkora": "23",
    "BEZÁRÁS": "EHR DOKUMENTUMOK"
  },
  {
    "Betegazonosító típusa": "TAJ szám",
    "Beteg azonosítója": "116086200",
    "Esemény típusa": "Járóbeteg-szakellátás megkezdése",
    "Ellátás státusza": "FELVETEL",
    "Ellátás kódja": "JARO",
    "Ellátás azonosítója": "231802281282976230",
    "Ellátó osztály": "001181334",
    "Ellátás kezdete": "2018.03.26. 09:11:08",
    "Ellátó orvos": "Hársing Judit (34171)",
    "Ambuláns ellátás típusa": "visszarendelés",
    "Beutaló osztály": "402123D",
    "Beutaló orvos": "Kuzmanovszki Daniella (66811)",
    "Ambuláns naplószám": "20001504",
    "BEZÁRÁS": "EHR DOKUMENTUMOK"
  },
  {
    "Betegazonosító típusa": "TAJ szám",
    "Beteg azonosítója": "116086200",
    "Esemény típusa": "Járóbeteg-szakellátás megkezdése",
    "Ellátás státusza": "FELVETEL",
    "Ellátás kódja": "JARO",
    "Ellátás azonosítója": "231802281270975199",
    "Ellátó osztály": "001181334",
    "Ellátás kezdete": "2018.03.26. 09:11:01",
    "Ellátó orvos": "Hársing Judit (34171)",
    "Ambuláns ellátás típusa": "visszarendelés",
    "Beutaló osztály": "402123D",
    "Beutaló orvos": "Kuzmanovszki Daniella (66811)",
    "Ambuláns naplószám": "20001503",
    "BEZÁRÁS": "EHR DOKUMENTUMOK"
  },
  {
    "Betegazonosító típusa": "TAJ szám",
    "Beteg azonosítója": "116086200",
    "Esemény típusa": "Háziorvosi ellátás megkezdése",
    "Ellátás státusza": "FELVETEL",
    "Ellátás kódja": "HAZIORVOS",
    "Ellátás azonosítója": "231800580758883479",
    "Ellátó intézmény": "Dr Benedek György Emilné",
    "Ellátó osztály": "háziorvosi ellátás",
    "Ellátás kezdete": "2018.01.23. 15:24:00",
    "Ellátó orvos": "Solynóczki Katalin (41492)",
    "BEZÁRÁS": "EHR DOKUMENTUMOK"
  },
  {
    "Betegazonosító típusa": "TAJ szám",
    "Beteg azonosítója": "116086200",
    "Esemény típusa": "Járóbeteg-szakellátás befejezése",
    "Ellátás státusza": "ELBOCSATAS",
    "Ellátás kódja": "JARO",
    "Ellátás azonosítója": "232304731872712170",
    "Ellátó intézmény": "ZUGLÓI EGÉSZSÉGÜGYI SZOLGÁLAT",
    "Ellátó osztály": "Bőrgyógyászati szakrendelés (gyermek)",
    "Ellátás kezdete": "2023.04.05. 08:01:00",
    "Ellátás vége": "2023.04.05. 08:08:22",
    "Ellátó orvos": "Taróczy Erika (37323)",
    "Ambuláns ellátás típusa": "első szakellátás az adott betegséggel kapcsolatban",
    "Beutaló intézmény": "ZUGLÓI EGÉSZSÉGÜGYI SZOLGÁLAT",
    "Beutaló osztály": "Bőrgyógyászati szakrendelés (gyermek)",
    "Beutaló orvos": "Taróczy Erika (37323)",
    "Iránydiagnózis": "Psoriasis, k.m.n. (L4090)",
    "Ambuláns naplószám": "00000456",
    "BEZÁRÁS": "EHR DOKUMENTUMOK"
  },
  {
    "Betegazonosító típusa": "TAJ szám",
    "Beteg azonosítója": "116086200",
    "Esemény típusa": "Járóbeteg-szakellátás befejezése",
    "Ellátás státusza": "ELBOCSATAS",
    "Ellátás kódja": "JARO",
    "Ellátás azonosítója": "232304651406428703",
    "Ellátó intézmény": "Taróczy-Med Szolgáltató Betéti Társaság",
    "Ellátó osztály": "Bőrgyógyászat",
    "Ellátás kezdete": "2023.04.03. 18:53:09",
    "Ellátás vége": "2023.04.03. 19:09:12",
    "Ellátó orvos": "Taróczy Erika (37323)",
    "Ambuláns ellátás típusa": "első szakellátás az adott betegséggel kapcsolatban",
    "Ambuláns naplószám": "04031016",
    "Ápolást indokló fődiagnózis": "Tinea unguium (B3510)",
    "Páciens megyéje": "Pest",
    "Páciens városa": "Nagykovácsi",
    "Páciens irányítószáma": "2094",
    "Páciens életkora": "23",
    "BEZÁRÁS": "EHR DOKUMENTUMOK"
  },
  {
    "Betegazonosító típusa": "TAJ szám",
    "Beteg azonosítója": "116086200",
    "Esemény típusa": "Laboratóriumi diagnosztikai vizsgálat lezárása",
    "Ellátás státusza": "LEZARAS",
    "Ellátás kódja": "LABOR",
    "Ellátás azonosítója": "232304521856225394",
    "Ellátó intézmény": "ÉSZAK-BUDAI SZENT JÁNOS CENTRUMKÓRHÁZ",
    "Ellátó osztály": "Központi laboratóriumi szakrendelés",
    "Ellátás kezdete": "2023.03.31. 09:39:00",
    "Ellátás vége": "2023.04.03. 11:22:00",
    "Ellátó orvos": "Csernák Zsolt József (49817)",
    "Beutaló intézmény": "Dr Benedek György Emilné",
    "Beutaló osztály": "háziorvosi ellátás",
    "Beutaló orvos": "Sólya Zsuzsanna (68436)",
    "Iránydiagnózis": "Angina pectoris egyéb formái (I2080)",
    "Ambuláns naplószám": "06065507",
    "Páciens megyéje": "Pest",
    "Páciens városa": "Nagykovácsi",
    "Páciens irányítószáma": "2094",
    "Páciens életkora": "23",
    "BEZÁRÁS": "EHR DOKUMENTUMOK"
  },
  {
    "Betegazonosító típusa": "TAJ szám",
    "Beteg azonosítója": "116086200",
    "Esemény típusa": "Háziorvosi ellátás befejezése",
    "Ellátás státusza": "ELBOCSATAS",
    "Ellátás kódja": "HAZIORVOS",
    "Ellátás azonosítója": "232303128346554221",
    "Ellátó intézmény": "Dr Benedek György Emilné",
    "Ellátó osztály": "háziorvosi ellátás",
    "Ellátás kezdete": "2023.03.03. 09:50:00",
    "Ellátás vége": "2023.03.03. 10:00:00",
    "Ellátó orvos": "Sólya Zsuzsanna (68436)",
    "Ápolást indokló fődiagnózis": "Angina pectoris egyéb formái (I2080)",
    "Páciens megyéje": "Pest",
    "Páciens városa": "Nagykovácsi",
    "Páciens irányítószáma": "2094",
    "Páciens életkora": "24",
    "BEZÁRÁS": "EHR DOKUMENTUMOK"
  },
  {
    "Betegazonosító típusa": "TAJ szám",
    "Beteg azonosítója": "116086200",
    "Esemény típusa": "Járóbeteg-szakellátás befejezése",
    "Ellátás státusza": "ELBOCSATAS",
    "Ellátás kódja": "JARO",
    "Ellátás azonosítója": "232301874613806891",
    "Ellátó intézmény": "ÉSZAK-BUDAI SZENT JÁNOS CENTRUMKÓRHÁZ",
    "Ellátó osztály": "Integrált Radiológiai Osztály - Röntgendiagnosztika",
    "Ellátás kezdete": "2023.02.08. 09:41:00",
    "Ellátás vége": "2023.02.14. 11:05:00",
    "Ellátó orvos": "Székely András (29994)",
    "Ambuláns ellátás típusa": "első szakellátás az adott betegséggel kapcsolatban",
    "Beutaló intézmény": "ÉSZAK-BUDAI SZENT JÁNOS CENTRUMKÓRHÁZ",
    "Beutaló osztály": "Ortopédiai szakambulancia",
    "Beutaló orvos": "Faggyas Ákos (50938)",
    "Iránydiagnózis": "Lúdtalp [pes planus] (szerzett) (M2140)",
    "Ambuláns továbbküldés": "továbbküldés nem történt",
    "Ambuláns naplószám": "03004207",
    "Páciens megyéje": "Pest",
    "Páciens városa": "Nagykovácsi",
    "Páciens irányítószáma": "2094",
    "Páciens életkora": "23",
    "BEZÁRÁS": "EHR DOKUMENTUMOK"
  },
  {
    "Betegazonosító típusa": "TAJ szám",
    "Beteg azonosítója": "116086200",
    "Esemény típusa": "Járóbeteg-szakellátás befejezése",
    "Ellátás státusza": "ELBOCSATAS",
    "Ellátás kódja": "JARO",
    "Ellátás azonosítója": "232301869584000197",
    "Ellátó intézmény": "ÉSZAK-BUDAI SZENT JÁNOS CENTRUMKÓRHÁZ",
    "Ellátó osztály": "Ortopédiai szakambulancia",
    "Ellátás kezdete": "2023.02.08. 09:10:00",
    "Ellátás vége": "2023.02.08. 09:53:00",
    "Ellátó orvos": "Faggyas Ákos (50938)",
    "Ambuláns ellátás típusa": "első szakellátás az adott betegséggel kapcsolatban",
    "Beutaló intézmény": "ÉSZAK-BUDAI SZENT JÁNOS CENTRUMKÓRHÁZ",
    "Beutaló osztály": "Ortopédiai szakambulancia",
    "Beutaló orvos": "Faggyas Ákos (50938)",
    "Iránydiagnózis": "Lúdtalp [pes planus] (szerzett) (M2140)",
    "Ambuláns továbbküldés": "továbbküldés nem történt",
    "Ambuláns naplószám": "01000833",
    "Páciens megyéje": "Pest",
    "Páciens városa": "Nagykovácsi",
    "Páciens irányítószáma": "2094",
    "Páciens életkora": "23",
    "BEZÁRÁS": "EHR DOKUMENTUMOK"
  },
  {
    "Betegazonosító típusa": "TAJ szám",
    "Beteg azonosítója": "116086200",
    "Esemény típusa": "Járóbeteg-szakellátás megkezdése",
    "Ellátás státusza": "FELVETEL",
    "Ellátás kódja": "JARO",
    "Ellátás azonosítója": "231802281282976230",
    "Ellátó osztály": "001181334",
    "Ellátás kezdete": "2018.03.26. 09:11:08",
    "Ellátó orvos": "Hársing Judit (34171)",
    "Ambuláns ellátás típusa": "visszarendelés",
    "Beutaló osztály": "402123D",
    "Beutaló orvos": "Kuzmanovszki Daniella (66811)",
    "Ambuláns naplószám": "20001504",
    "BEZÁRÁS": "EHR DOKUMENTUMOK"
  },
  {
    "Betegazonosító típusa": "TAJ szám",
    "Beteg azonosítója": "116086200",
    "Esemény típusa": "Járóbeteg-szakellátás megkezdése",
    "Ellátás státusza": "FELVETEL",
    "Ellátás kódja": "JARO",
    "Ellátás azonosítója": "231802281270975199",
    "Ellátó osztály": "001181334",
    "Ellátás kezdete": "2018.03.26. 09:11:01",
    "Ellátó orvos": "Hársing Judit (34171)",
    "Ambuláns ellátás típusa": "visszarendelés",
    "Beutaló osztály": "402123D",
    "Beutaló orvos": "Kuzmanovszki Daniella (66811)",
    "Ambuláns naplószám": "20001503",
    "BEZÁRÁS": "EHR DOKUMENTUMOK"
  },
  {
    "Betegazonosító típusa": "TAJ szám",
    "Beteg azonosítója": "116086200",
    "Esemény típusa": "Háziorvosi ellátás megkezdése",
    "Ellátás státusza": "FELVETEL",
    "Ellátás kódja": "HAZIORVOS",
    "Ellátás azonosítója": "231800580758883479",
    "Ellátó intézmény": "Dr Benedek György Emilné",
    "Ellátó osztály": "háziorvosi ellátás",
    "Ellátás kezdete": "2018.01.23. 15:24:00",
    "Ellátó orvos": "Solynóczki Katalin (41492)",
    "BEZÁRÁS": "EHR DOKUMENTUMOK"
  },
  {
    "Betegazonosító típusa": "TAJ szám",
    "Beteg azonosítója": "116086200",
    "Esemény típusa": "Járóbeteg-szakellátás befejezése",
    "Ellátás státusza": "ELBOCSATAS",
    "Ellátás kódja": "JARO",
    "Ellátás azonosítója": "232306662913290932",
    "Ellátó intézmény": "BUDAPESTI SZENT FERENC KORHÁZ",
    "Ellátó osztály": "EKG vizsgálatok",
    "Ellátás kezdete": "2023.05.16. 13:04:00",
    "Ellátás vége": "2023.05.16. 13:04:00",
    "Ellátó orvos": "Tury Peregrin Ákos (66712)",
    "Ambuláns ellátás típusa": "szakorvosi konzílium",
    "Iránydiagnózis": "Palpitatio (R0020)",
    "Ambuláns naplószám": "40001804",
    "BEZÁRÁS": "EHR DOKUMENTUMOK"
  },
  {
    "Betegazonosító típusa": "TAJ szám",
    "Beteg azonosítója": "116086200",
    "Esemény típusa": "Járóbeteg-szakellátás befejezése",
    "Ellátás státusza": "ELBOCSATAS",
    "Ellátás kódja": "JARO",
    "Ellátás azonosítója": "232306662155826025",
    "Ellátó intézmény": "BUDAPESTI SZENT FERENC KORHÁZ",
    "Ellátó osztály": "Kardiológiai járóbeteg szakrendelés",
    "Ellátás kezdete": "2023.05.16. 13:00:00",
    "Ellátás vége": "2023.05.16. 13:00:00",
    "Ellátó orvos": "Tury Peregrin Ákos (66712)",
    "Ambuláns ellátás típusa": "első szakellátás az adott betegséggel kapcsolatban",
    "Iránydiagnózis": "Palpitatio (R0020)",
    "Ambuláns naplószám": "40003431",
    "BEZÁRÁS": "EHR DOKUMENTUMOK"
  },
  {
    "Betegazonosító típusa": "TAJ szám",
    "Beteg azonosítója": "116086200",
    "Esemény típusa": "Járóbeteg-szakellátás megkezdése",
    "Ellátás státusza": "FELVETEL",
    "Ellátás kódja": "JARO",
    "Ellátás azonosítója": "231802281282976230",
    "Ellátó osztály": "001181334",
    "Ellátás kezdete": "2018.03.26. 09:11:08",
    "Ellátó orvos": "Hársing Judit (34171)",
    "Ambuláns ellátás típusa": "visszarendelés",
    "Beutaló osztály": "402123D",
    "Beutaló orvos": "Kuzmanovszki Daniella (66811)",
    "Ambuláns naplószám": "20001504",
    "BEZÁRÁS": "EHR DOKUMENTUMOK"
  },
  {
    "Betegazonosító típusa": "TAJ szám",
    "Beteg azonosítója": "116086200",
    "Esemény típusa": "Járóbeteg-szakellátás megkezdése",
    "Ellátás státusza": "FELVETEL",
    "Ellátás kódja": "JARO",
    "Ellátás azonosítója": "231802281270975199",
    "Ellátó osztály": "001181334",
    "Ellátás kezdete": "2018.03.26. 09:11:01",
    "Ellátó orvos": "Hársing Judit (34171)",
    "Ambuláns ellátás típusa": "visszarendelés",
    "Beutaló osztály": "402123D",
    "Beutaló orvos": "Kuzmanovszki Daniella (66811)",
    "Ambuláns naplószám": "20001503",
    "BEZÁRÁS": "EHR DOKUMENTUMOK"
  },
  {
    "Betegazonosító típusa": "TAJ szám",
    "Beteg azonosítója": "116086200",
    "Esemény típusa": "Háziorvosi ellátás megkezdése",
    "Ellátás státusza": "FELVETEL",
    "Ellátás kódja": "HAZIORVOS",
    "Ellátás azonosítója": "231800580758883479",
    "Ellátó intézmény": "Dr Benedek György Emilné",
    "Ellátó osztály": "háziorvosi ellátás",
    "Ellátás kezdete": "2018.01.23. 15:24:00",
    "Ellátó orvos": "Solynóczki Katalin (41492)",
    "BEZÁRÁS": "EHR DOKUMENTUMOK"
  },
  {
    "Betegazonosító típusa": "TAJ szám",
    "Beteg azonosítója": "116086200",
    "Esemény típusa": "Járóbeteg-szakellátás befejezése",
    "Ellátás státusza": "ELBOCSATAS",
    "Ellátás kódja": "JARO",
    "Ellátás azonosítója": "232403168197158132",
    "Ellátó intézmény": "Synlab Hungary Korlátolt Felelősségű Társaság",
    "Ellátó osztály": "Klinikai Kémia Laboratórium II. prog.",
    "Ellátás kezdete": "2024.03.01. 11:39:30",
    "Ellátás vége": "2024.03.01. 11:39:30",
    "Ellátó orvos": "Konderák Judit (48902)",
    "Ambuláns ellátás típusa": "első szakellátás az adott betegséggel kapcsolatban",
    "Beutaló osztály": "001223554",
    "Ambuláns naplószám": "05027760",
    "BEZÁRÁS": "EHR DOKUMENTUMOK"
  },
  {
    "Betegazonosító típusa": "TAJ szám",
    "Beteg azonosítója": "116086200",
    "Esemény típusa": "Járóbeteg-szakellátás befejezése",
    "Ellátás státusza": "ELBOCSATAS",
    "Ellátás kódja": "JARO",
    "Ellátás azonosítója": "232403127065119318",
    "Ellátó intézmény": "Synlab Hungary Korlátolt Felelősségű Társaság",
    "Ellátó osztály": "Klinikai Kémia Laboratórium II. prog.",
    "Ellátás kezdete": "2024.02.29. 23:47:12",
    "Ellátás vége": "2024.02.29. 23:47:12",
    "Ellátó orvos": "Konderák Judit (48902)",
    "Ambuláns ellátás típusa": "első szakellátás az adott betegséggel kapcsolatban",
    "Beutaló osztály": "001223554",
    "Ambuláns naplószám": "05027808",
    "BEZÁRÁS": "EHR DOKUMENTUMOK"
  },
  {
    "Betegazonosító típusa": "TAJ szám",
    "Beteg azonosítója": "116086200",
    "Esemény típusa": "Járóbeteg-szakellátás befejezése",
    "Ellátás státusza": "ELBOCSATAS",
    "Ellátás kódja": "JARO",
    "Ellátás azonosítója": "232402235324868204",
    "Ellátó intézmény": "Synlab Hungary Korlátolt Felelősségű Társaság",
    "Ellátó osztály": "Klinikai Kémia Laboratórium II. prog.",
    "Ellátás kezdete": "2024.02.14. 01:18:38",
    "Ellátás vége": "2024.02.14. 01:18:38",
    "Ellátó orvos": "Konderák Judit (48902)",
    "Ambuláns ellátás típusa": "első szakellátás az adott betegséggel kapcsolatban",
    "Beutaló osztály": "001223554",
    "Ambuláns naplószám": "04960624",
    "BEZÁRÁS": "EHR DOKUMENTUMOK"
  },
  {
    "Betegazonosító típusa": "TAJ szám",
    "Beteg azonosítója": "116086200",
    "Esemény típusa": "Járóbeteg-szakellátás befejezése",
    "Ellátás státusza": "ELBOCSATAS",
    "Ellátás kódja": "JARO",
    "Ellátás azonosítója": "232316348380863882",
    "Ellátó intézmény": "ÉSZAK-BUDAI SZENT JÁNOS CENTRUMKÓRHÁZ",
    "Ellátó osztály": "Fül-orr-gégészeti szakambulancia",
    "Ellátás kezdete": "2023.12.12. 09:12:00",
    "Ellátás vége": "2023.12.12. 09:34:00",
    "Ellátó orvos": "Szalai György (44199)",
    "Ambuláns ellátás típusa": "első szakellátás az adott betegséggel kapcsolatban",
    "Beutaló intézmény": "ÉSZAK-BUDAI SZENT JÁNOS CENTRUMKÓRHÁZ",
    "Beutaló osztály": "Fül-orr-gégészeti szakambulancia",
    "Beutaló orvos": "Szalai György (44199)",
    "Iránydiagnózis": "Status post sanationem (U9920)",
    "Ambuláns továbbküldés": "továbbküldés nem történt",
    "Ambuláns naplószám": "01008425",
    "Páciens megyéje": "Pest",
    "Páciens városa": "Nagykovácsi",
    "Páciens irányítószáma": "2094",
    "Páciens életkora": "24",
    "BEZÁRÁS": "EHR DOKUMENTUMOK"
  },
  {
    "Betegazonosító típusa": "TAJ szám",
    "Beteg azonosítója": "116086200",
    "Esemény típusa": "Járóbeteg-szakellátás befejezése",
    "Ellátás státusza": "ELBOCSATAS",
    "Ellátás kódja": "JARO",
    "Ellátás azonosítója": "232316246674613899",
    "Ellátó osztály": "000005087",
    "Ellátás kezdete": "2023.12.06. 11:37:00",
    "Ellátás vége": "2023.12.11. 10:09:00",
    "Ellátó orvos": "Szabó Huba Zoltán (63682)",
    "Ambuláns ellátás típusa": "első szakellátás az adott betegséggel kapcsolatban",
    "Beutaló intézmény": "ÉSZAK-BUDAI SZENT JÁNOS CENTRUMKÓRHÁZ",
    "Beutaló osztály": "Fül-orr-gégészeti Osztály",
    "Beutaló orvos": "Szalai György (44199)",
    "Iránydiagnózis": "Idült garatmandula-gyulladás (J3500)",
    "Ambuláns továbbküldés": "továbbküldés nem történt",
    "Ambuláns naplószám": "07010639",
    "Páciens megyéje": "Pest",
    "Páciens városa": "Nagykovácsi",
    "Páciens irányítószáma": "2094",
    "Páciens életkora": "24",
    "BEZÁRÁS": "EHR DOKUMENTUMOK"
  },
  {
    "Betegazonosító típusa": "TAJ szám",
    "Beteg azonosítója": "116086200",
    "Esemény típusa": "Fekvőbeteg-szakellátás befejezése",
    "Ellátás státusza": "ELBOCSATAS",
    "Ellátás kódja": "FEKVO",
    "Ellátás azonosítója": "232316038160213618",
    "Ellátó intézmény": "ÉSZAK-BUDAI SZENT JÁNOS CENTRUMKÓRHÁZ",
    "Ellátó osztály": "Fül-orr-gégészeti Osztály",
    "Szakmakód": "fül-orr-gégegyógyászat (0600)",
    "Ellátás kezdete": "2023.12.06. 07:23:00",
    "Ellátás vége": "2023.12.07. 11:30:00",
    "Ellátó orvos": "Szalai György (44199)",
    "Fekvőbeteg felvétel típusa": "nem sürgős ellátás, ideértve a pszichiátriai beteg felvételét rendőrségi közreműködés nélkül",
    "Fekvőbeteg felvétel jellege": "saját intézet járóbeteg-szakellátó munkahelye beutalta",
    "Beutaló intézmény": "ÉSZAK-BUDAI SZENT JÁNOS CENTRUMKÓRHÁZ",
    "Beutaló osztály": "Fül-orr-gégészeti szakambulancia",
    "Beutaló orvos": "Szalai György (44199)",
    "Iránydiagnózis": "Idült garatmandula-gyulladás (J3500)",
    "Páciens további sorsa": "otthonába bocsátva / az intézeten kívüli szülés szak-mai szabályairól, feltételeiről és kizáró okairól szóló kormányrendelet szerinti ellátást nyújtó egészségügyi szolgáltató által nyújtott ellátás befejezettnek minősül",
    "Törzsszám": "202335506",
    "Ápolási sorszám": "0",
    "Ápolást indokló fődiagnózis": "Idült garatmandula-gyulladás (J3500)",
    "Páciens megyéje": "Pest",
    "Páciens városa": "Nagykovácsi",
    "Páciens irányítószáma": "2094",
    "Páciens életkora": "24",
    "BEZÁRÁS": "EHR DOKUMENTUMOK"
  },
  {
    "Betegazonosító típusa": "TAJ szám",
    "Beteg azonosítója": "116086200",
    "Esemény típusa": "Laboratóriumi diagnosztikai vizsgálat lezárása",
    "Ellátás státusza": "LEZARAS",
    "Ellátás kódja": "LABOR",
    "Ellátás azonosítója": "232315845143404201",
    "Ellátó osztály": "001018749",
    "Ellátás kezdete": "2023.12.01. 11:42:00",
    "Ellátás vége": "2023.12.01. 13:38:00",
    "Ellátó orvos": "Makács Zsuzsanna Márta (41505)",
    "Beutaló intézmény": "ÉSZAK-BUDAI SZENT JÁNOS CENTRUMKÓRHÁZ",
    "Beutaló osztály": "Fül-orr-gégészeti szakambulancia",
    "Beutaló orvos": "Szalai György (44199)",
    "Iránydiagnózis": "Idült garatmandula-gyulladás (J3500)",
    "Ambuláns naplószám": "04233456",
    "Páciens megyéje": "Pest",
    "Páciens városa": "Nagykovácsi",
    "Páciens irányítószáma": "2094",
    "Páciens életkora": "24",
    "BEZÁRÁS": "EHR DOKUMENTUMOK"
  },
  {
    "Betegazonosító típusa": "TAJ szám",
    "Beteg azonosítója": "116086200",
    "Esemény típusa": "Laboratóriumi diagnosztikai vizsgálat lezárása",
    "Ellátás státusza": "LEZARAS",
    "Ellátás kódja": "LABOR",
    "Ellátás azonosítója": "232315834426895810",
    "Ellátó intézmény": "ÉSZAK-BUDAI SZENT JÁNOS CENTRUMKÓRHÁZ",
    "Ellátó osztály": "Központi laboratóriumi szakrendelés",
    "Ellátás kezdete": "2023.12.01. 10:25:00",
    "Ellátás vége": "2023.12.01. 17:45:00",
    "Ellátó orvos": "Csernák Zsolt József (49817)",
    "Beutaló intézmény": "ÉSZAK-BUDAI SZENT JÁNOS CENTRUMKÓRHÁZ",
    "Beutaló osztály": "Fül-orr-gégészeti szakambulancia",
    "Beutaló orvos": "Szalai György (44199)",
    "Iránydiagnózis": "Idült garatmandula-gyulladás (J3500)",
    "Ambuláns naplószám": "06233355",
    "Páciens megyéje": "Pest",
    "Páciens városa": "Nagykovácsi",
    "Páciens irányítószáma": "2094",
    "Páciens életkora": "24",
    "BEZÁRÁS": "EHR DOKUMENTUMOK"
  },
  {
    "Betegazonosító típusa": "TAJ szám",
    "Beteg azonosítója": "116086200",
    "Esemény típusa": "Járóbeteg-szakellátás befejezése",
    "Ellátás státusza": "ELBOCSATAS",
    "Ellátás kódja": "JARO",
    "Ellátás azonosítója": "232315801711000541",
    "Ellátó intézmény": "Belvárosi Orvosi Centrum Korlátolt Felelősségű Társaság",
    "Ellátó osztály": "Urológia rendelés",
    "Ellátás kezdete": "2023.11.30. 17:02:04",
    "Ellátás vége": "2023.11.30. 17:13:57",
    "Ellátó orvos": "Varju Viktor (69923)",
    "Ambuláns ellátás típusa": "első szakellátás az adott betegséggel kapcsolatban",
    "Ambuláns naplószám": "31130085",
    "BEZÁRÁS": "EHR DOKUMENTUMOK"
  },
  {
    "Betegazonosító típusa": "TAJ szám",
    "Beteg azonosítója": "116086200",
    "Esemény típusa": "Járóbeteg-szakellátás befejezése",
    "Ellátás státusza": "ELBOCSATAS",
    "Ellátás kódja": "JARO",
    "Ellátás azonosítója": "232315497781360672",
    "Ellátó intézmény": "GutMed Egészségügyi Szolgáltató Korlátolt Felelősségű Társaság",
    "Ellátó osztály": "Gasztroenterológia",
    "Ellátás kezdete": "2023.11.22. 08:23:57",
    "Ellátás vége": "2023.11.22. 08:30:37",
    "Ellátó orvos": "Schwab Richárd Ernő (54273)",
    "Ambuláns ellátás típusa": "első szakellátás az adott betegséggel kapcsolatban",
    "Ambuláns naplószám": "31122011",
    "BEZÁRÁS": "EHR DOKUMENTUMOK"
  },
  {
    "Betegazonosító típusa": "TAJ szám",
    "Beteg azonosítója": "116086200",
    "Esemény típusa": "Járóbeteg-szakellátás befejezése",
    "Ellátás státusza": "ELBOCSATAS",
    "Ellátás kódja": "JARO",
    "Ellátás azonosítója": "232314286524927435",
    "Ellátó intézmény": "Synlab Hungary Korlátolt Felelősségű Társaság",
    "Ellátó osztály": "Klinikai Kémia Laboratórium II. prog.",
    "Ellátás kezdete": "2023.11.01. 17:30:20",
    "Ellátás vége": "2023.11.01. 17:30:22",
    "Ellátó orvos": "Konderák Judit (48902)",
    "Ambuláns ellátás típusa": "első szakellátás az adott betegséggel kapcsolatban",
    "Beutaló osztály": "001223554",
    "Beutaló orvos": "Schwab Richárd Ernő (54273)",
    "Ambuláns naplószám": "04544880",
    "BEZÁRÁS": "EHR DOKUMENTUMOK"
  },
  {
    "Betegazonosító típusa": "TAJ szám",
    "Beteg azonosítója": "116086200",
    "Esemény típusa": "Járóbeteg-szakellátás befejezése",
    "Ellátás státusza": "ELBOCSATAS",
    "Ellátás kódja": "JARO",
    "Ellátás azonosítója": "232314165862187706",
    "Ellátó intézmény": "ÉSZAK-BUDAI SZENT JÁNOS CENTRUMKÓRHÁZ",
    "Ellátó osztály": "Fül-orr-gégészeti szakambulancia",
    "Ellátás kezdete": "2023.10.30. 09:05:00",
    "Ellátás vége": "2023.10.30. 09:11:00",
    "Ellátó orvos": "Szalai György (44199)",
    "Ambuláns ellátás típusa": "első szakellátás az adott betegséggel kapcsolatban",
    "Beutaló intézmény": "ÉSZAK-BUDAI SZENT JÁNOS CENTRUMKÓRHÁZ",
    "Beutaló osztály": "Fül-orr-gégészeti szakambulancia",
    "Beutaló orvos": "Szalai György (44199)",
    "Iránydiagnózis": "Idült garatmandula-gyulladás (J3500)",
    "Ambuláns továbbküldés": "továbbküldés nem történt",
    "Ambuláns naplószám": "01007398",
    "Páciens megyéje": "Pest",
    "Páciens városa": "Nagykovácsi",
    "Páciens irányítószáma": "2094",
    "Páciens életkora": "24",
    "BEZÁRÁS": "EHR DOKUMENTUMOK"
  },
  {
    "Betegazonosító típusa": "TAJ szám",
    "Beteg azonosítója": "116086200",
    "Esemény típusa": "Járóbeteg-szakellátás befejezése",
    "Ellátás státusza": "ELBOCSATAS",
    "Ellátás kódja": "JARO",
    "Ellátás azonosítója": "232313759720503626",
    "Ellátó intézmény": "Synlab Hungary Korlátolt Felelősségű Társaság",
    "Ellátó osztály": "Klinikai Kémia Laboratórium II. prog.",
    "Ellátás kezdete": "2023.10.19. 12:41:53",
    "Ellátás vége": "2023.10.19. 12:41:53",
    "Ellátó orvos": "Konderák Judit (48902)",
    "Ambuláns ellátás típusa": "első szakellátás az adott betegséggel kapcsolatban",
    "Beutaló osztály": "001223554",
    "Beutaló orvos": "Schwab Richárd Ernő (54273)",
    "Ambuláns naplószám": "04544916",
    "BEZÁRÁS": "EHR DOKUMENTUMOK"
  },
  {
    "Betegazonosító típusa": "TAJ szám",
    "Beteg azonosítója": "116086200",
    "Esemény típusa": "Járóbeteg-szakellátás befejezése",
    "Ellátás státusza": "ELBOCSATAS",
    "Ellátás kódja": "JARO",
    "Ellátás azonosítója": "232313429416144094",
    "Ellátó intézmény": "Synlab Hungary Korlátolt Felelősségű Társaság",
    "Ellátó osztály": "Klinikai Kémia Laboratórium II. prog.",
    "Ellátás kezdete": "2023.10.16. 16:20:03",
    "Ellátás vége": "2023.10.16. 16:20:08",
    "Ellátó orvos": "Konderák Judit (48902)",
    "Ambuláns ellátás típusa": "első szakellátás az adott betegséggel kapcsolatban",
    "Beutaló osztály": "001223554",
    "Beutaló orvos": "Schwab Richárd Ernő (54273)",
    "Ambuláns naplószám": "04534255",
    "BEZÁRÁS": "EHR DOKUMENTUMOK"
  },
  {
    "Betegazonosító típusa": "TAJ szám",
    "Beteg azonosítója": "116086200",
    "Esemény típusa": "Háziorvosi ellátás befejezése",
    "Ellátás státusza": "ELBOCSATAS",
    "Ellátás kódja": "HAZIORVOS",
    "Ellátás azonosítója": "232313521675232711",
    "Ellátó intézmény": "Dr Benedek György Emilné",
    "Ellátó osztály": "háziorvosi ellátás",
    "Ellátás kezdete": "2023.10.16. 09:59:00",
    "Ellátás vége": "2023.10.16. 10:06:00",
    "Ellátó orvos": "Sólya Zsuzsanna (68436)",
    "Ápolást indokló fődiagnózis": "Psoriasis vulgaris (L4000)",
    "Páciens megyéje": "Pest",
    "Páciens városa": "Nagykovácsi",
    "Páciens irányítószáma": "2094",
    "Páciens életkora": "24",
    "BEZÁRÁS": "EHR DOKUMENTUMOK"
  },
  {
    "Betegazonosító típusa": "TAJ szám",
    "Beteg azonosítója": "116086200",
    "Esemény típusa": "Járóbeteg-szakellátás befejezése",
    "Ellátás státusza": "ELBOCSATAS",
    "Ellátás kódja": "JARO",
    "Ellátás azonosítója": "232313334637086875",
    "Ellátó intézmény": "MIND Klinika Korlátolt Felelősségű Társaság",
    "Ellátó osztály": "Gasztroenterológiai rendelés",
    "Ellátás kezdete": "2023.10.11. 12:22:53",
    "Ellátás vége": "2023.10.11. 12:38:13",
    "Ellátó orvos": "Gelley András (36240)",
    "Ambuláns ellátás típusa": "első szakellátás az adott betegséggel kapcsolatban",
    "Ambuláns naplószám": "31011040",
    "BEZÁRÁS": "EHR DOKUMENTUMOK"
  },
  {
    "Betegazonosító típusa": "TAJ szám",
    "Beteg azonosítója": "116086200",
    "Esemény típusa": "Háziorvosi ellátás befejezése",
    "Ellátás státusza": "ELBOCSATAS",
    "Ellátás kódja": "HAZIORVOS",
    "Ellátás azonosítója": "232312801777260704",
    "Ellátó intézmény": "Dr Benedek György Emilné",
    "Ellátó osztály": "háziorvosi ellátás",
    "Ellátás kezdete": "2023.10.02. 09:07:00",
    "Ellátás vége": "2023.10.02. 09:20:00",
    "Ellátó orvos": "Sólya Zsuzsanna (68436)",
    "Ápolást indokló fődiagnózis": "Psoriasis vulgaris (L4000)",
    "Páciens megyéje": "Pest",
    "Páciens városa": "Nagykovácsi",
    "Páciens irányítószáma": "2094",
    "Páciens életkora": "24",
    "BEZÁRÁS": "EHR DOKUMENTUMOK"
  },
  {
    "Betegazonosító típusa": "TAJ szám",
    "Beteg azonosítója": "116086200",
    "Esemény típusa": "Járóbeteg-szakellátás megkezdése",
    "Ellátás státusza": "FELVETEL",
    "Ellátás kódja": "JARO",
    "Ellátás azonosítója": "231802281282976230",
    "Ellátó osztály": "001181334",
    "Ellátás kezdete": "2018.03.26. 09:11:08",
    "Ellátó orvos": "Hársing Judit (34171)",
    "Ambuláns ellátás típusa": "visszarendelés",
    "Beutaló osztály": "402123D",
    "Beutaló orvos": "Kuzmanovszki Daniella (66811)",
    "Ambuláns naplószám": "20001504",
    "BEZÁRÁS": "EHR DOKUMENTUMOK"
  },
  {
    "Betegazonosító típusa": "TAJ szám",
    "Beteg azonosítója": "116086200",
    "Esemény típusa": "Járóbeteg-szakellátás megkezdése",
    "Ellátás státusza": "FELVETEL",
    "Ellátás kódja": "JARO",
    "Ellátás azonosítója": "231802281270975199",
    "Ellátó osztály": "001181334",
    "Ellátás kezdete": "2018.03.26. 09:11:01",
    "Ellátó orvos": "Hársing Judit (34171)",
    "Ambuláns ellátás típusa": "visszarendelés",
    "Beutaló osztály": "402123D",
    "Beutaló orvos": "Kuzmanovszki Daniella (66811)",
    "Ambuláns naplószám": "20001503",
    "BEZÁRÁS": "EHR DOKUMENTUMOK"
  },
  {
    "Betegazonosító típusa": "TAJ szám",
    "Beteg azonosítója": "116086200",
    "Esemény típusa": "Háziorvosi ellátás megkezdése",
    "Ellátás státusza": "FELVETEL",
    "Ellátás kódja": "HAZIORVOS",
    "Ellátás azonosítója": "231800580758883479",
    "Ellátó intézmény": "Dr Benedek György Emilné",
    "Ellátó osztály": "háziorvosi ellátás",
    "Ellátás kezdete": "2018.01.23. 15:24:00",
    "Ellátó orvos": "Solynóczki Katalin (41492)",
    "BEZÁRÁS": "EHR DOKUMENTUMOK"
  },
  {
    "Betegazonosító típusa": "TAJ szám",
    "Beteg azonosítója": "116086200",
    "Esemény típusa": "Járóbeteg-szakellátás befejezése",
    "Ellátás státusza": "ELBOCSATAS",
    "Ellátás kódja": "JARO",
    "Ellátás azonosítója": "232405317974815618",
    "Ellátó intézmény": "Synlab Hungary Korlátolt Felelősségű Társaság",
    "Ellátó osztály": "Klinikai Kémia Laboratórium II. prog.",
    "Ellátás kezdete": "2024.04.15. 19:44:33",
    "Ellátás vége": "2024.04.15. 19:44:33",
    "Ellátó orvos": "Konderák Judit (48902)",
    "Ambuláns ellátás típusa": "első szakellátás az adott betegséggel kapcsolatban",
    "Beutaló osztály": "001223554",
    "Ambuláns naplószám": "05187367",
    "BEZÁRÁS": "EHR DOKUMENTUMOK"
  },
  {
    "Betegazonosító típusa": "TAJ szám",
    "Beteg azonosítója": "116086200",
    "Esemény típusa": "Járóbeteg-szakellátás megkezdése",
    "Ellátás státusza": "FELVETEL",
    "Ellátás kódja": "JARO",
    "Ellátás azonosítója": "231802281282976230",
    "Ellátó osztály": "001181334",
    "Ellátás kezdete": "2018.03.26. 09:11:08",
    "Ellátó orvos": "Hársing Judit (34171)",
    "Ambuláns ellátás típusa": "visszarendelés",
    "Beutaló osztály": "402123D",
    "Beutaló orvos": "Kuzmanovszki Daniella (66811)",
    "Ambuláns naplószám": "20001504",
    "BEZÁRÁS": "EHR DOKUMENTUMOK"
  },
  {
    "Betegazonosító típusa": "TAJ szám",
    "Beteg azonosítója": "116086200",
    "Esemény típusa": "Járóbeteg-szakellátás megkezdése",
    "Ellátás státusza": "FELVETEL",
    "Ellátás kódja": "JARO",
    "Ellátás azonosítója": "231802281270975199",
    "Ellátó osztály": "001181334",
    "Ellátás kezdete": "2018.03.26. 09:11:01",
    "Ellátó orvos": "Hársing Judit (34171)",
    "Ambuláns ellátás típusa": "visszarendelés",
    "Beutaló osztály": "402123D",
    "Beutaló orvos": "Kuzmanovszki Daniella (66811)",
    "Ambuláns naplószám": "20001503",
    "BEZÁRÁS": "EHR DOKUMENTUMOK"
  },
  {
    "Betegazonosító típusa": "TAJ szám",
    "Beteg azonosítója": "116086200",
    "Esemény típusa": "Háziorvosi ellátás megkezdése",
    "Ellátás státusza": "FELVETEL",
    "Ellátás kódja": "HAZIORVOS",
    "Ellátás azonosítója": "231800580758883479",
    "Ellátó intézmény": "Dr Benedek György Emilné",
    "Ellátó osztály": "háziorvosi ellátás",
    "Ellátás kezdete": "2018.01.23. 15:24:00",
    "Ellátó orvos": "Solynóczki Katalin (41492)",
    "BEZÁRÁS": "EHR DOKUMENTUMOK"
  },
  {
    "Betegazonosító típusa": "TAJ szám",
    "Beteg azonosítója": "116086200",
    "Esemény típusa": "Járóbeteg-szakellátás megkezdése",
    "Ellátás státusza": "FELVETEL",
    "Ellátás kódja": "JARO",
    "Ellátás azonosítója": "231802281282976230",
    "Ellátó osztály": "001181334",
    "Ellátás kezdete": "2018.03.26. 09:11:08",
    "Ellátó orvos": "Hársing Judit (34171)",
    "Ambuláns ellátás típusa": "visszarendelés",
    "Beutaló osztály": "402123D",
    "Beutaló orvos": "Kuzmanovszki Daniella (66811)",
    "Ambuláns naplószám": "20001504",
    "BEZÁRÁS": "EHR DOKUMENTUMOK"
  },
  {
    "Betegazonosító típusa": "TAJ szám",
    "Beteg azonosítója": "116086200",
    "Esemény típusa": "Járóbeteg-szakellátás megkezdése",
    "Ellátás státusza": "FELVETEL",
    "Ellátás kódja": "JARO",
    "Ellátás azonosítója": "231802281270975199",
    "Ellátó osztály": "001181334",
    "Ellátás kezdete": "2018.03.26. 09:11:01",
    "Ellátó orvos": "Hársing Judit (34171)",
    "Ambuláns ellátás típusa": "visszarendelés",
    "Beutaló osztály": "402123D",
    "Beutaló orvos": "Kuzmanovszki Daniella (66811)",
    "Ambuláns naplószám": "20001503",
    "BEZÁRÁS": "EHR DOKUMENTUMOK"
  },
  {
    "Betegazonosító típusa": "TAJ szám",
    "Beteg azonosítója": "116086200",
    "Esemény típusa": "Háziorvosi ellátás megkezdése",
    "Ellátás státusza": "FELVETEL",
    "Ellátás kódja": "HAZIORVOS",
    "Ellátás azonosítója": "231800580758883479",
    "Ellátó intézmény": "Dr Benedek György Emilné",
    "Ellátó osztály": "háziorvosi ellátás",
    "Ellátás kezdete": "2018.01.23. 15:24:00",
    "Ellátó orvos": "Solynóczki Katalin (41492)",
    "BEZÁRÁS": "EHR DOKUMENTUMOK"
  },
  {
    "Betegazonosító típusa": "TAJ szám",
    "Beteg azonosítója": "116086200",
    "Esemény típusa": "Járóbeteg-szakellátás befejezése",
    "Ellátás státusza": "ELBOCSATAS",
    "Ellátás kódja": "JARO",
    "Ellátás azonosítója": "232512369991775313",
    "Ellátó intézmény": "ÉSZAK-BUDAI SZENT JÁNOS CENTRUMKÓRHÁZ",
    "Ellátó osztály": "Traumatológiai szakrendelés",
    "Ellátás kezdete": "2025.09.01. 16:07:00",
    "Ellátás vége": "2025.09.01. 17:00:00",
    "Ellátó orvos": "Gera Ákos (87711)",
    "Ambuláns ellátás típusa": "első szakellátás az adott betegséggel kapcsolatban",
    "Beutaló intézmény": "ÉSZAK-BUDAI SZENT JÁNOS CENTRUMKÓRHÁZ",
    "Beutaló osztály": "Traumatológiai Szakrendelés II",
    "Beutaló orvos": "Gera Ákos (87711)",
    "Iránydiagnózis": "A kéz ujj(-ak) nyílt sebe a köröm sérülése nélkül (S6100)",
    "Ambuláns továbbküldés": "továbbküldés nem történt",
    "Ambuláns naplószám": "01011545",
    "Páciens megyéje": "Pest",
    "Páciens városa": "Nagykovácsi",
    "Páciens irányítószáma": "2094",
    "Páciens életkora": "26",
    "BEZÁRÁS": "EHR DOKUMENTUMOK"
  },
  {
    "Betegazonosító típusa": "TAJ szám",
    "Beteg azonosítója": "116086200",
    "Esemény típusa": "Járóbeteg-szakellátás befejezése",
    "Ellátás státusza": "ELBOCSATAS",
    "Ellátás kódja": "JARO",
    "Ellátás azonosítója": "232512269191470363",
    "Ellátó intézmény": "ÉSZAK-BUDAI SZENT JÁNOS CENTRUMKÓRHÁZ",
    "Ellátó osztály": "Kútvölgyi Allergológiai és Immunológiai szakrendelés",
    "Ellátás kezdete": "2025.08.29. 10:52:00",
    "Ellátás vége": "2025.08.29. 11:35:00",
    "Ellátó orvos": "Temesszentandrási György (55446)",
    "Ambuláns ellátás típusa": "első szakellátás az adott betegséggel kapcsolatban",
    "Beutaló intézmény": "Dr Benedek György Emilné",
    "Beutaló osztály": "háziorvosi ellátás",
    "Beutaló orvos": "Sólya Zsuzsanna (68436)",
    "Iránydiagnózis": "Allergia, k.m.n. (T7840)",
    "Ambuláns továbbküldés": "továbbküldés nem történt",
    "Ambuláns naplószám": "01000520",
    "Páciens megyéje": "Pest",
    "Páciens városa": "Nagykovácsi",
    "Páciens irányítószáma": "2094",
    "Páciens életkora": "26",
    "BEZÁRÁS": "EHR DOKUMENTUMOK"
  },
  {
    "Betegazonosító típusa": "TAJ szám",
    "Beteg azonosítója": "116086200",
    "Esemény típusa": "Járóbeteg-szakellátás befejezése",
    "Ellátás státusza": "ELBOCSATAS",
    "Ellátás kódja": "JARO",
    "Ellátás azonosítója": "232512292575449837",
    "Ellátó intézmény": "Synlab Hungary Korlátolt Felelősségű Társaság",
    "Ellátó osztály": "Klinikai Kémia Laboratórium II. prog.",
    "Ellátás kezdete": "2025.08.29. 00:00:00",
    "Ellátás vége": "2025.09.01. 12:14:13",
    "Ellátó orvos": "Konderák Judit (48902)",
    "Ambuláns ellátás típusa": "első szakellátás az adott betegséggel kapcsolatban",
    "Beutaló osztály": "010622902",
    "Beutaló orvos": "Temesszentandrási György (55446)",
    "Ambuláns naplószám": "00061574",
    "BEZÁRÁS": "EHR DOKUMENTUMOK"
  },
  {
    "Betegazonosító típusa": "TAJ szám",
    "Beteg azonosítója": "116086200",
    "Esemény típusa": "Háziorvosi ellátás befejezése",
    "Ellátás státusza": "ELBOCSATAS",
    "Ellátás kódja": "HAZIORVOS",
    "Ellátás azonosítója": "232508728268506484",
    "Ellátó intézmény": "DR. SÓLYA ZSUZSANNA",
    "Ellátó osztály": "Felnőtt háziorvosi alapellátás",
    "Ellátás kezdete": "2025.06.12. 08:06:29",
    "Ellátás vége": "2025.06.12. 08:11:20",
    "Ellátó orvos": "Sólya Zsuzsanna (68436)",
    "Ambuláns ellátás típusa": "első szakellátás az adott betegséggel kapcsolatban",
    "Iránydiagnózis": "Vizsgálat: vérnyomás (Z0130)",
    "BEZÁRÁS": "EHR DOKUMENTUMOK"
  },
  {
    "Betegazonosító típusa": "TAJ szám",
    "Beteg azonosítója": "116086200",
    "Esemény típusa": "Háziorvosi ellátás megkezdése",
    "Ellátás státusza": "FELVETEL",
    "Ellátás kódja": "HAZIORVOS",
    "Ellátás azonosítója": "232508728268442571",
    "Ellátó intézmény": "DR. SÓLYA ZSUZSANNA",
    "Ellátó osztály": "Felnőtt háziorvosi alapellátás",
    "Ellátás kezdete": "2025.06.12. 08:06:29",
    "Ellátó orvos": "Sólya Zsuzsanna (68436)",
    "Ambuláns ellátás típusa": "első szakellátás az adott betegséggel kapcsolatban",
    "Iránydiagnózis": "Sine morbo (U9990)",
    "BEZÁRÁS": "EHR DOKUMENTUMOK"
  },
  {
    "Betegazonosító típusa": "TAJ szám",
    "Beteg azonosítója": "116086200",
    "Esemény típusa": "Háziorvosi ellátás befejezése",
    "Ellátás státusza": "ELBOCSATAS",
    "Ellátás kódja": "HAZIORVOS",
    "Ellátás azonosítója": "232508693843516867",
    "Ellátó intézmény": "DR. SÓLYA ZSUZSANNA",
    "Ellátó osztály": "Felnőtt háziorvosi alapellátás",
    "Ellátás kezdete": "2025.06.11. 12:39:10",
    "Ellátás vége": "2025.06.11. 12:59:10",
    "Ellátó orvos": "Sólya Zsuzsanna (68436)",
    "Ambuláns ellátás típusa": "első szakellátás az adott betegséggel kapcsolatban",
    "Iránydiagnózis": "Psoriasis vulgaris, kp.súlyos (PASI-SCOR 11-18) (L4003)",
    "BEZÁRÁS": "EHR DOKUMENTUMOK"
  },
  {
    "Betegazonosító típusa": "TAJ szám",
    "Beteg azonosítója": "116086200",
    "Esemény típusa": "Járóbeteg-szakellátás befejezése",
    "Ellátás státusza": "ELBOCSATAS",
    "Ellátás kódja": "JARO",
    "Ellátás azonosítója": "232504068420682804",
    "Ellátó intézmény": "Synlab Hungary Korlátolt Felelősségű Társaság",
    "Ellátó osztály": "Klinikai Kémia Laboratórium II. prog.",
    "Ellátás kezdete": "2025.03.14. 13:08:29",
    "Ellátás vége": "2025.03.14. 13:08:29",
    "Ellátó orvos": "Konderák Judit (48902)",
    "Ambuláns ellátás típusa": "első szakellátás az adott betegséggel kapcsolatban",
    "Beutaló osztály": "001223554",
    "Ambuláns naplószám": "00401472",
    "BEZÁRÁS": "EHR DOKUMENTUMOK"
  },
  {
    "Betegazonosító típusa": "TAJ szám",
    "Beteg azonosítója": "116086200",
    "Esemény típusa": "Járóbeteg-szakellátás megkezdése",
    "Ellátás státusza": "FELVETEL",
    "Ellátás kódja": "JARO",
    "Ellátás azonosítója": "231802281282976230",
    "Ellátó osztály": "001181334",
    "Ellátás kezdete": "2018.03.26. 09:11:08",
    "Ellátó orvos": "Hársing Judit (34171)",
    "Ambuláns ellátás típusa": "visszarendelés",
    "Beutaló osztály": "402123D",
    "Beutaló orvos": "Kuzmanovszki Daniella (66811)",
    "Ambuláns naplószám": "20001504",
    "BEZÁRÁS": "EHR DOKUMENTUMOK"
  },
  {
    "Betegazonosító típusa": "TAJ szám",
    "Beteg azonosítója": "116086200",
    "Esemény típusa": "Járóbeteg-szakellátás megkezdése",
    "Ellátás státusza": "FELVETEL",
    "Ellátás kódja": "JARO",
    "Ellátás azonosítója": "231802281270975199",
    "Ellátó osztály": "001181334",
    "Ellátás kezdete": "2018.03.26. 09:11:01",
    "Ellátó orvos": "Hársing Judit (34171)",
    "Ambuláns ellátás típusa": "visszarendelés",
    "Beutaló osztály": "402123D",
    "Beutaló orvos": "Kuzmanovszki Daniella (66811)",
    "Ambuláns naplószám": "20001503",
    "BEZÁRÁS": "EHR DOKUMENTUMOK"
  },
  {
    "Betegazonosító típusa": "TAJ szám",
    "Beteg azonosítója": "116086200",
    "Esemény típusa": "Háziorvosi ellátás megkezdése",
    "Ellátás státusza": "FELVETEL",
    "Ellátás kódja": "HAZIORVOS",
    "Ellátás azonosítója": "231800580758883479",
    "Ellátó intézmény": "Dr Benedek György Emilné",
    "Ellátó osztály": "háziorvosi ellátás",
    "Ellátás kezdete": "2018.01.23. 15:24:00",
    "Ellátó orvos": "Solynóczki Katalin (41492)",
    "BEZÁRÁS": "EHR DOKUMENTUMOK"
  },
  {
    "Betegazonosító típusa": "TAJ szám",
    "Beteg azonosítója": "116086200",
    "Esemény típusa": "Járóbeteg-szakellátás befejezése",
    "Ellátás státusza": "ELBOCSATAS",
    "Ellátás kódja": "JARO",
    "Ellátás azonosítója": "232512541353417376",
    "Ellátó intézmény": "ÉSZAK-BUDAI SZENT JÁNOS CENTRUMKÓRHÁZ",
    "Ellátó osztály": "Kútvölgyi Belgyógyászati szakrendelés II.",
    "Ellátás kezdete": "2025.09.04. 08:06:00",
    "Ellátás vége": "2025.09.04. 08:51:00",
    "Ellátó orvos": "Temesszentandrási György (55446)",
    "Ambuláns ellátás típusa": "első szakellátás az adott betegséggel kapcsolatban",
    "Beutaló intézmény": "ÉSZAK-BUDAI SZENT JÁNOS CENTRUMKÓRHÁZ",
    "Beutaló osztály": "Kútvölgyi Belgyógyászati szakrendelés II.",
    "Beutaló orvos": "Temesszentandrási György (55446)",
    "Iránydiagnózis": "Allergia, k.m.n. (T7840)",
    "Ambuláns továbbküldés": "továbbküldés nem történt",
    "Ambuláns naplószám": "01004388",
    "Páciens megyéje": "Pest",
    "Páciens városa": "Nagykovácsi",
    "Páciens irányítószáma": "2094",
    "Páciens életkora": "26",
    "BEZÁRÁS": "EHR DOKUMENTUMOK"
  },
  {
    "Betegazonosító típusa": "TAJ szám",
    "Beteg azonosítója": "116086200",
    "Esemény típusa": "Háziorvosi ellátás megkezdése",
    "Ellátás státusza": "FELVETEL",
    "Ellátás kódja": "HAZIORVOS",
    "Ellátás azonosítója": "232508728268442571",
    "Ellátó intézmény": "DR. SÓLYA ZSUZSANNA",
    "Ellátó osztály": "Felnőtt háziorvosi alapellátás",
    "Ellátás kezdete": "2025.06.12. 08:06:29",
    "Ellátó orvos": "Sólya Zsuzsanna (68436)",
    "Ambuláns ellátás típusa": "első szakellátás az adott betegséggel kapcsolatban",
    "Iránydiagnózis": "Sine morbo (U9990)",
    "BEZÁRÁS": "EHR DOKUMENTUMOK"
  },
  {
    "Betegazonosító típusa": "TAJ szám",
    "Beteg azonosítója": "116086200",
    "Esemény típusa": "Járóbeteg-szakellátás megkezdése",
    "Ellátás státusza": "FELVETEL",
    "Ellátás kódja": "JARO",
    "Ellátás azonosítója": "231802281282976230",
    "Ellátó osztály": "001181334",
    "Ellátás kezdete": "2018.03.26. 09:11:08",
    "Ellátó orvos": "Hársing Judit (34171)",
    "Ambuláns ellátás típusa": "visszarendelés",
    "Beutaló osztály": "402123D",
    "Beutaló orvos": "Kuzmanovszki Daniella (66811)",
    "Ambuláns naplószám": "20001504",
    "BEZÁRÁS": "EHR DOKUMENTUMOK"
  },
  {
    "Betegazonosító típusa": "TAJ szám",
    "Beteg azonosítója": "116086200",
    "Esemény típusa": "Járóbeteg-szakellátás megkezdése",
    "Ellátás státusza": "FELVETEL",
    "Ellátás kódja": "JARO",
    "Ellátás azonosítója": "231802281270975199",
    "Ellátó osztály": "001181334",
    "Ellátás kezdete": "2018.03.26. 09:11:01",
    "Ellátó orvos": "Hársing Judit (34171)",
    "Ambuláns ellátás típusa": "visszarendelés",
    "Beutaló osztály": "402123D",
    "Beutaló orvos": "Kuzmanovszki Daniella (66811)",
    "Ambuláns naplószám": "20001503",
    "BEZÁRÁS": "EHR DOKUMENTUMOK"
  },
  {
    "Betegazonosító típusa": "TAJ szám",
    "Beteg azonosítója": "116086200",
    "Esemény típusa": "Háziorvosi ellátás megkezdése",
    "Ellátás státusza": "FELVETEL",
    "Ellátás kódja": "HAZIORVOS",
    "Ellátás azonosítója": "231800580758883479",
    "Ellátó intézmény": "Dr Benedek György Emilné",
    "Ellátó osztály": "háziorvosi ellátás",
    "Ellátás kezdete": "2018.01.23. 15:24:00",
    "Ellátó orvos": "Solynóczki Katalin (41492)",
    "BEZÁRÁS": "EHR DOKUMENTUMOK"
  }
]